{
  "name": "orbit",
  "description": "Satellite's orbit classification and/or description. Period is measured in years",
  "fields": [
    {
      "name": "reference",
      "hidden": true,
      "type": "url",
      "allowedValues": [],
      "required": true
    },
    {
      "name": "verified",
      "hidden": true,
      "description": "",
      "type": "string",
      "allowedValues": ["true", "false"]
    },
    {
      "name": "orbit",
      "type": "string",
      "allowedValues": ["GEO", "LEO", "HEO", "SSO", "Polar", "GTO"],
      "required": true
    },
    {
      "name": "description",
      "type": "string",
      "allowedValues": [],
      "stringMax": 255
    },
    {
      "name": "period",
      "type": "number",
      "allowedValues": []
    }
  ]
}
