{
  "_id": "48drLMA5afDNQBZeL",
  "noradID": "31307",
  "isDeleted": false,
  "createdOn": "2021-10-05T21:33:37.270Z",
  "createdBy": "admin",
  "modifiedOn": "2021-10-05T21:51:55.522Z",
  "modifiedBy": "admin",
  "adminCheck": true,
  "machineCheck": false,
  "names": [
    {
      "reference": "https://www.n2yo.com/satellite/?s=31307",
      "verified": [
        {
          "method": "user",
          "name": "admin",
          "verified": true,
          "verifiedOn": "2021-10-07T00:00:00.000Z"
        },
        {
          "method": "machine",
          "name": "Layer8",
          "verified": false,
          "verifiedOn": ""
        }
      ],
      "validated": [
        {
          "method": "user",
          "name": "admin",
          "validated": true,
          "validatedOn": "2021-10-07T00:00:00.000Z"
        },
        {
          "method": "machine",
          "name": "Layer8",
          "validated": false,
          "validatedOn": ""
        }
      ],
      "name": "GALAXY 17"
    }
  ],
  "types": [
    {
      "reference": "https://en.wikipedia.org/wiki/Galaxy_17",
      "verified": [
        {
          "method": "user",
          "name": "admin",
          "verified": true,
          "verifiedOn": "2021-10-07T00:00:00.000Z"
        },
        {
          "method": "machine",
          "name": "Layer8",
          "verified": false,
          "verifiedOn": ""
        }
      ],
      "validated": [
        {
          "method": "user",
          "name": "admin",
          "validated": true,
          "validatedOn": "2021-10-07T00:00:00.000Z"
        },
        {
          "method": "machine",
          "name": "Layer8",
          "validated": false,
          "validatedOn": ""
        }
      ],
      "type": "communications"
    }
  ],
  "descriptionShort": [
    {
      "reference": "https://en.wikipedia.org/wiki/Galaxy_17",
      "verified": [
        {
          "method": "user",
          "name": "admin",
          "verified": true,
          "verifiedOn": "2021-10-07T00:00:00.000Z"
        },
        {
          "method": "machine",
          "name": "Layer8",
          "verified": false,
          "verifiedOn": ""
        }
      ],
      "validated": [
        {
          "method": "user",
          "name": "admin",
          "validated": true,
          "validatedOn": "2021-10-07T00:00:00.000Z"
        },
        {
          "method": "machine",
          "name": "Layer8",
          "validated": false,
          "validatedOn": ""
        }
      ],
      "descriptionShort": "Galaxy 17 is a communications satellite owned by Intelsat to be located at 91° West longitude, serving the North American market."
    }
  ],
  "images": [
    {
      "reference": "https://www.arianespace.com/wp-content/uploads/2016/11/missionup_17apr07_sm.jpg",
      "verified": [
        {
          "method": "user",
          "name": "admin",
          "verified": true,
          "verifiedOn": "2021-10-07T00:00:00.000Z"
        },
        {
          "method": "machine",
          "name": "Layer8",
          "verified": false,
          "verifiedOn": ""
        }
      ],
      "validated": [
        {
          "method": "user",
          "name": "admin",
          "validated": true,
          "validatedOn": "2021-10-07T00:00:00.000Z"
        },
        {
          "method": "machine",
          "name": "Layer8",
          "validated": false,
          "validatedOn": ""
        }
      ],
      "description": "Galaxy 17 is \"topped off\" in the Spaceport's S5 payload preparation building",
      "url": "https://www.arianespace.com/wp-content/uploads/2016/11/missionup_17apr07_sm.jpg",
      "entireSatellite": "true"
    }
  ],
  "transponder": [
    {
      "reference": "https://www.arianespace.com/mission-update/galaxy-17-is-topped-off-in-the-spaceports-s5-payload-preparation-building/",
      "verified": [
        {
          "method": "user",
          "name": "admin",
          "verified": true,
          "verifiedOn": "2021-10-07T00:00:00.000Z"
        },
        {
          "method": "machine",
          "name": "Layer8",
          "verified": false,
          "verifiedOn": ""
        }
      ],
      "validated": [
        {
          "method": "user",
          "name": "admin",
          "validated": true,
          "validatedOn": "2021-10-07T00:00:00.000Z"
        },
        {
          "method": "machine",
          "name": "Layer8",
          "validated": false,
          "validatedOn": ""
        }
      ],
      "description": "24 C-Band transponders",
      "minBand": "4",
      "maxBand": "8",
      "bandScale": "Ghz",
      "direction": ""
    },
    {
      "reference": "https://www.arianespace.com/mission-update/galaxy-17-is-topped-off-in-the-spaceports-s5-payload-preparation-building/",
      "verified": [
        {
          "method": "user",
          "name": "admin",
          "verified": true,
          "verifiedOn": "2021-10-07T00:00:00.000Z"
        },
        {
          "method": "machine",
          "name": "Layer8",
          "verified": false,
          "verifiedOn": ""
        }
      ],
      "validated": [
        {
          "method": "user",
          "name": "admin",
          "validated": true,
          "validatedOn": "2021-10-07T00:00:00.000Z"
        },
        {
          "method": "machine",
          "name": "Layer8",
          "validated": false,
          "validatedOn": ""
        }
      ],
      "description": "24 Ku-Band transponders",
      "minBand": "12",
      "maxBand": "18",
      "bandScale": "Ghz",
      "direction": ""
    }
  ],
  "orbit": [
    {
      "reference": "https://www.arianespace.com/mission-update/galaxy-17-is-topped-off-in-the-spaceports-s5-payload-preparation-building/",
      "verified": [
        {
          "method": "user",
          "name": "admin",
          "verified": true,
          "verifiedOn": "2021-10-07T00:00:00.000Z"
        },
        {
          "method": "machine",
          "name": "Layer8",
          "verified": false,
          "verifiedOn": ""
        }
      ],
      "validated": [
        {
          "method": "user",
          "name": "admin",
          "validated": true,
          "validatedOn": "2021-10-07T00:00:00.000Z"
        },
        {
          "method": "machine",
          "name": "Layer8",
          "validated": false,
          "validatedOn": ""
        }
      ],
      "orbit": "GEO",
      "description": ""
    }
  ]
}
